redataprocessing/__init__.py
redataprocessing/sreality.py
redataprocessing/sreality_api_dictionaries.py
redataprocessing/sreality_description_asyncio.py
redataprocessing/sreality_description_download_decoding.py
redataprocessing/tests/test.py
redataprocessing-0.0.24.dist-info/LICENSE
redataprocessing-0.0.24.dist-info/METADATA
redataprocessing-0.0.24.dist-info/WHEEL
redataprocessing-0.0.24.dist-info/top_level.txt
redataprocessing-0.0.24.dist-info/RECORD
